__init__.py
mongo_pckg/__init__.py
mongo_pckg/mongo_crud.py
mongo_pckg-0.0.4.dist-info/METADATA
mongo_pckg-0.0.4.dist-info/WHEEL
mongo_pckg-0.0.4.dist-info/top_level.txt
mongo_pckg-0.0.4.dist-info/RECORD
